TempDirectoryContext/TempDirectoryContext.py
TempDirectoryContext/__init__.py
TempDirectoryContext-1.0.1.dist-info/DESCRIPTION.rst
TempDirectoryContext-1.0.1.dist-info/METADATA
TempDirectoryContext-1.0.1.dist-info/RECORD
TempDirectoryContext-1.0.1.dist-info/WHEEL
TempDirectoryContext-1.0.1.dist-info/metadata.json
TempDirectoryContext-1.0.1.dist-info/top_level.txt
