Metadata-Version: 2.0
Name: TempDirectoryContext
Version: 1.0.1
Summary: A context manager around the creation of temporary directories
Home-page: http://tempdirectorycontext.readthedocs.io/en/latest/
Author: Tony Flury
Author-email: anthony.flury@btinternet.com
License: GNU General Public License (GPL)
Keywords: Testing,Context Manager
Platform: UNKNOWN
Classifier: Development Status :: 5 - Production/Stable
Classifier: Intended Audience :: Developers
Classifier: License :: OSI Approved :: GNU General Public License (GPL)
Classifier: Programming Language :: Python :: 2.7
Classifier: Programming Language :: Python :: 3.5
Classifier: Topic :: Software Development :: Testing
Provides-Extra: dev
Requires-Dist: check-manifest; extra == 'dev'
Provides-Extra: test
Requires-Dist: coverage; extra == 'test'
